collective.smtpssl-2.0-py3.11-nspkg.pth
collective/smtpssl/__init__.py
collective/smtpssl/configure.zcml
collective/smtpssl/interfaces.py
collective/smtpssl/permissions.zcml
collective/smtpssl/setuphandlers.py
collective/smtpssl/testing.py
collective/smtpssl/locales/README.rst
collective/smtpssl/locales/__init__.py
collective/smtpssl/locales/collective.smtpssl.pot
collective/smtpssl/locales/update.py
collective/smtpssl/locales/update.sh
collective/smtpssl/locales/en/LC_MESSAGES/collective.smtpssl.po
collective/smtpssl/profiles/default/browserlayer.xml
collective/smtpssl/profiles/default/metadata.xml
collective/smtpssl/profiles/uninstall/browserlayer.xml
collective/smtpssl/tests/__init__.py
collective/smtpssl/tests/test_setup.py
collective/smtpssl/tests/robot/test_example.robot
collective.smtpssl-2.0.dist-info/LICENSE.GPL
collective.smtpssl-2.0.dist-info/LICENSE.rst
collective.smtpssl-2.0.dist-info/METADATA
collective.smtpssl-2.0.dist-info/WHEEL
collective.smtpssl-2.0.dist-info/entry_points.txt
collective.smtpssl-2.0.dist-info/namespace_packages.txt
collective.smtpssl-2.0.dist-info/top_level.txt
collective.smtpssl-2.0.dist-info/RECORD
