Metadata-Version: 2.2
Name: collective.smtpssl
Version: 2.0
Summary: Patches zope.sendmail.mailer.SMTPMailer to use smtplib.SMTP_SSL instead of smtplib.SMTP, to support sending oder port 465.
Home-page: https://github.com/collective/collective.smtpssl
Author: Maik Derstappen
Author-email: md@derico.de
License: GPL version 2
Project-URL: PyPI, https://pypi.org/project/collective.smtpssl/
Project-URL: Source, https://github.com/collective/collective.smtpssl
Project-URL: Tracker, https://github.com/collective/collective.smtpssl/issues
Keywords: Python Plone CMS
Classifier: Environment :: Web Environment
Classifier: Framework :: Plone
Classifier: Framework :: Plone :: Addon
Classifier: Framework :: Plone :: 6.1
Classifier: Programming Language :: Python
Classifier: Programming Language :: Python :: 3.9
Classifier: Programming Language :: Python :: 3.10
Classifier: Programming Language :: Python :: 3.11
Classifier: Programming Language :: Python :: 3.12
Classifier: Operating System :: OS Independent
Classifier: License :: OSI Approved :: GNU General Public License v2 (GPLv2)
Requires-Python: >=3.9
License-File: LICENSE.GPL
License-File: LICENSE.rst
Requires-Dist: setuptools
Requires-Dist: collective.monkeypatcher
Requires-Dist: zope.sendmail>=6.2
Requires-Dist: Products.MailHost>=6.0
Provides-Extra: test
Requires-Dist: plone.app.testing; extra == "test"
Requires-Dist: plone.testing>=5.0.0; extra == "test"
Dynamic: author
Dynamic: author-email
Dynamic: classifier
Dynamic: description
Dynamic: home-page
Dynamic: keywords
Dynamic: license
Dynamic: project-url
Dynamic: provides-extra
Dynamic: requires-dist
Dynamic: requires-python
Dynamic: summary
